argyaml/__init__.py
argyaml/__main__.py
argyaml/base.py
argyaml/cli-config.yaml
argyaml/handlers/_generate.py
argyaml-0.1.6.dist-info/LICENSE
argyaml-0.1.6.dist-info/METADATA
argyaml-0.1.6.dist-info/WHEEL
argyaml-0.1.6.dist-info/entry_points.txt
argyaml-0.1.6.dist-info/RECORD
